TwitchBotPlus/__init__.py
TwitchBotPlus/core.py
TwitchBotPlus/modules/__init__.py
TwitchBotPlus/modules/auth.py
TwitchBotPlus/modules/command_handler.py
TwitchBotPlus/modules/data_clases.py
TwitchBotPlus/modules/networking.py
TwitchBotPlus/modules/twitch.py
twitch_bot_plus-1.1.0.dist-info/licenses/LICENSE
twitch_bot_plus-1.1.0.dist-info/METADATA
twitch_bot_plus-1.1.0.dist-info/WHEEL
twitch_bot_plus-1.1.0.dist-info/top_level.txt
twitch_bot_plus-1.1.0.dist-info/RECORD
