Metadata-Version: 2.4
Name: twitch-bot-plus
Version: 1.1.0
Summary: A modular Twitch chat bot framework.
Author-email: Bearium <ContactMe@bearium.dev>
License-Expression: MIT
Keywords: twitch,bot,irc,chat
Classifier: Programming Language :: Python :: 3
Classifier: Operating System :: OS Independent
Requires-Python: >=3.10
License-File: LICENSE
Requires-Dist: python-dotenv>=1.0
Requires-Dist: requests>=2.32
Dynamic: license-file
